aiodatastore/__init__.py
aiodatastore/client.py
aiodatastore/commit.py
aiodatastore/constants.py
aiodatastore/entity.py
aiodatastore/filters.py
aiodatastore/key.py
aiodatastore/lookup.py
aiodatastore/mutation.py
aiodatastore/property.py
aiodatastore/query.py
aiodatastore/transaction.py
aiodatastore/values.py
aiodatastore-0.2.0.dist-info/METADATA
aiodatastore-0.2.0.dist-info/WHEEL
aiodatastore-0.2.0.dist-info/licenses/LICENSE
aiodatastore-0.2.0.dist-info/RECORD
