Metadata-Version: 2.1
Name: aiodatastore
Version: 0.2.0
Summary: Low level and high performance asyncio client for Google Datastore REST API
Project-URL: Homepage, https://github.com/umax/aiodatastore
Project-URL: Source, https://github.com/umax/aiodatastore
Project-URL: Changelog, https://github.com/umax/aiodatastore/blob/main/CHANGELOG.md
Author-email: Max Usachev <maxusachev@gmail.com>
License-File: LICENSE
Classifier: Development Status :: 5 - Production/Stable
Classifier: Framework :: AsyncIO
Classifier: License :: OSI Approved :: MIT License
Classifier: Operating System :: OS Independent
Classifier: Programming Language :: Python :: 3
Classifier: Programming Language :: Python :: 3.8
Classifier: Programming Language :: Python :: 3.9
Classifier: Programming Language :: Python :: 3.10
Classifier: Programming Language :: Python :: 3.11
Classifier: Topic :: Software Development :: Libraries :: Python Modules
Requires-Python: >=3.8
Requires-Dist: gcloud-aio-auth<5.0.0,>=3.1.0
